Metadata-Version: 1.1
Name: TFBOYS
Version: 0.0.1
Summary: TensorFlow BOYS
Home-page: https://github.com/nypisces/TFBOYS
Author: NY
Author-email: nypisces@live.com
License: MIT
Platform: UNKNOWN
Classifier: Environment :: Web Environment
Classifier: Intended Audience :: Developers
Classifier: License :: OSI Approved :: MIT License
Classifier: Operating System :: OS Independent
Classifier: Programming Language :: Python
Classifier: Programming Language :: Python :: 3.5
Classifier: Programming Language :: Python :: 3.6
Classifier: Topic :: Internet :: WWW/HTTP
Classifier: Topic :: Internet :: WWW/HTTP :: Dynamic Content
